eis_toolkit/__init__.py
eis_toolkit/__main__.py
eis_toolkit/cli.py
eis_toolkit/conversions/__init__.py
eis_toolkit/conversions/csv_to_geodataframe.py
eis_toolkit/conversions/raster_to_dataframe.py
eis_toolkit/evaluation/__init__.py
eis_toolkit/evaluation/calculate_base_metrics.py
eis_toolkit/evaluation/classification_label_evaluation.py
eis_toolkit/evaluation/classification_probability_evaluation.py
eis_toolkit/evaluation/plot_confusion_matrix.py
eis_toolkit/evaluation/plot_nn_model_performance.py
eis_toolkit/evaluation/plot_prediction_area_curves.py
eis_toolkit/evaluation/plot_rate_curve.py
eis_toolkit/evaluation/scoring.py
eis_toolkit/exceptions.py
eis_toolkit/exploratory_analyses/__init__.py
eis_toolkit/exploratory_analyses/basic_plots_seaborn.py
eis_toolkit/exploratory_analyses/chi_square_test.py
eis_toolkit/exploratory_analyses/correlation_matrix.py
eis_toolkit/exploratory_analyses/covariance_matrix.py
eis_toolkit/exploratory_analyses/dbscan.py
eis_toolkit/exploratory_analyses/descriptive_statistics.py
eis_toolkit/exploratory_analyses/feature_importance.py
eis_toolkit/exploratory_analyses/k_means_cluster.py
eis_toolkit/exploratory_analyses/local_morans_i.py
eis_toolkit/exploratory_analyses/normality_test.py
eis_toolkit/exploratory_analyses/parallel_coordinates.py
eis_toolkit/exploratory_analyses/pca.py
eis_toolkit/exploratory_analyses/plot_utils.py
eis_toolkit/prediction/__init__.py
eis_toolkit/prediction/fuzzy_overlay.py
eis_toolkit/prediction/gradient_boosting.py
eis_toolkit/prediction/logistic_regression.py
eis_toolkit/prediction/machine_learning_general.py
eis_toolkit/prediction/machine_learning_predict.py
eis_toolkit/prediction/mlp.py
eis_toolkit/prediction/random_forests.py
eis_toolkit/prediction/weights_of_evidence.py
eis_toolkit/raster_processing/__init__.py
eis_toolkit/raster_processing/clipping.py
eis_toolkit/raster_processing/create_constant_raster.py
eis_toolkit/raster_processing/derivatives/__init__.py
eis_toolkit-1.1.6.dist-info/LICENSE
eis_toolkit-1.1.6.dist-info/METADATA
eis_toolkit-1.1.6.dist-info/WHEEL
eis_toolkit-1.1.6.dist-info/entry_points.txt
eis_toolkit-1.1.6.dist-info/RECORD
