Metadata-Version: 2.1
Name: eis_toolkit
Version: 1.1.6
Summary: EIS Toolkit is a comprehensive collection of tools suitable for mineral prospectivity mapping. This toolkit has been developed as part of the Exploration Information System project which has been funded by European Union.
Home-page: https://eis-he.eu
License: EUPL-1.2
Keywords: Development Status :: 4 - Beta,Topic :: Scientific/Engineering :: GIS,Programming Language :: Python :: 3 :: Only
Maintainer: Gispo Ltd.
Maintainer-email: info@gispo.fi
Requires-Python: >=3.9,<3.11
Classifier: License :: OSI Approved :: European Union Public Licence 1.2 (EUPL 1.2)
Classifier: Programming Language :: Python :: 3
Classifier: Programming Language :: Python :: 3.9
Classifier: Programming Language :: Python :: 3.10
Requires-Dist: beartype (>=0.13.1,<0.14.0)
Requires-Dist: esda (>=2.5.1,<3.0.0)
Requires-Dist: fiona (<1.10.0)
Requires-Dist: gdal (>=3.4.3,<4.0.0)
Requires-Dist: geopandas (>=0.11.1,<0.12.0)
Requires-Dist: imbalanced-learn (>=0.11.0,<0.12.0)
Requires-Dist: keras (>=2.9.0,<3.0.0)
Requires-Dist: matplotlib (>=3.5.3,<4.0.0)
Requires-Dist: numba (>=0.60.0,<0.61.0)
Requires-Dist: pandas (>=2.0.0,<3.0.0)
Requires-Dist: pykrige (>=1.7.0,<2.0.0)
Requires-Dist: pysal (>=23.7,<24.0)
Requires-Dist: rasterio (>=1.3.0,<2.0.0)
Requires-Dist: rtree (>=1.0.1,<2.0.0)
Requires-Dist: scikit-learn (>=1.1.2,<2.0.0)
Requires-Dist: scipy (==1.11.4)
Requires-Dist: seaborn (>=0.13.0,<1.0.0)
Requires-Dist: statsmodels (>=0.14.0,<0.15.0)
Requires-Dist: tensorflow (>=2.9.1,<3.0.0)
Requires-Dist: typer[all] (>=0.9.0,<0.10.0)
Project-URL: Repository, https://github.com/GispoCoding/eis_toolkit
Project-URL: issues, https://github.com/GispoCoding/eis_toolkit/issues
